{
  "Version": "1.0",
  "ModID": "Taludas_sharedgood_potash",
  "DeprecateIds": [],
  "ModDependencies": [
    "Taludas_sharedproduct_potash"
  ],
  "LoadAfterIds": [
    "Taludas_sharedproduct_potash"
  ],
  "IncompatibleIds": null,
  "Category": {
    "English": "Shared",
    "Chinese": "Shared",
    "French": "Shared",
    "German": "Shared",
    "Italian": "Shared",
    "Japanese": "Shared",
    "Korean": "Shared",
    "Polish": "Shared",
    "Russian": "Shared",
    "Spanish": "Shared",
    "Taiwanese": "Shared"
  },
  "ModName": {
    "Chinese": "sharedgood_potash (Taludas)",
    "English": "sharedgood_potash (Taludas)",
    "French": "sharedgood_potash (Taludas)",
    "German": " sharedgood_potash (Taludas)",
    "Italian": "sharedgood_potash (Taludas)",
    "Japanese": "sharedgood_potash (Taludas)",
    "Korean": "sharedgood_potash (Taludas)",
    "Polish": "sharedgood_potash (Taludas)",
    "Russian": "sharedgood_potash (Taludas)",
    "Spanish": "sharedgood_potash (Taludas)",
    "Taiwanese": "sharedgood_potash (Taludas)"
  },
  "Description": {
    "English": "# Extra Goods \n\n Extra Goods implemented by me for use in some of my mods. \n\n - Potash",
    "German": "# Extra Goods \n\n Zusätzliche Waren, die von mir für einige meiner Mods implementiert wurden. \n\n - Pottasche",
    "Chinese": null,
    "French": null,
    "Italian": null,
    "Japanese": null,
    "Korean": null,
    "Polish": null,
    "Russian": null,
    "Spanish": null,
    "Taiwanese": null
  },
  "KnownIssues": null,
  "DLCDependencies": [
  ],
  "CreatorName": "Taludas",
  "Image": null
}